kubernety-0.1.0.dist-info/METADATA
kubernety-0.1.0.dist-info/WHEEL
kubernety-0.1.0.dist-info/entry_points.txt
kubernety-0.1.0.dist-info/licenses/LICENSE
kubernety/__init__.py
kubernety/custom_widgets.py
kubernety/gui.py
kubernety/logs.py
kubernety/main.py
kubernety/pods.py
kubernety/style.css
kubernety/utils.py
kubernety-0.1.0.dist-info/RECORD
