Metadata-Version: 2.1
Name: kubernety
Version: 0.1.0
Summary: Graphical interface for Kubernetes API in your console
Author-Email: Mariano Carrazana <marianocarrazana@gmail.com>
License: MIT
Project-URL: Bug tracker, https://github.com/marianocarrazana/kubernety/issues
Project-URL: Source code, https://github.com/marianocarrazana/kubernety
Requires-Python: >=3.9
Requires-Dist: textual>=0.28.0
Requires-Dist: click>=8.1.3
Requires-Dist: pyyaml>=6.0
Requires-Dist: kubernetes>=26.1.0
